fastapi_react_cli.py
fastapi_weblauncher-0.1.2.dist-info/METADATA
fastapi_weblauncher-0.1.2.dist-info/WHEEL
fastapi_weblauncher-0.1.2.dist-info/entry_points.txt
fastapi_weblauncher-0.1.2.dist-info/top_level.txt
fastapi_weblauncher-0.1.2.dist-info/RECORD
